snakey/__main__.py
snakey/utils.py
snakey/res/config.json
snakey-2.1.0.dist-info/LICENSE.txt
snakey-2.1.0.dist-info/METADATA
snakey-2.1.0.dist-info/WHEEL
snakey-2.1.0.dist-info/entry_points.txt
snakey-2.1.0.dist-info/top_level.txt
snakey-2.1.0.dist-info/RECORD
