Metadata-Version: 2.1
Name: snakey
Version: 2.1.0
Summary: A simple snake game written in python.
Author-email: Jost Prevc <jost.prevc@gmail.com>
License: MIT
Keywords: snake,pygame
Classifier: Programming Language :: Python :: 3
Requires-Python: >=3.7
License-File: LICENSE.txt
Requires-Dist: pygame (==2.1.3.dev8)
Provides-Extra: dev
Requires-Dist: pytest ; extra == 'dev'
Requires-Dist: pylint ; extra == 'dev'
Requires-Dist: pre-commit ; extra == 'dev'
Requires-Dist: black[d] ; extra == 'dev'
Requires-Dist: mypy ; extra == 'dev'
Requires-Dist: tox ; extra == 'dev'
Provides-Extra: test
Requires-Dist: pytest ; extra == 'test'
